markgdoc/__init__.py
markgdoc/__main__.py
markgdoc/markgdoc.py
markgdoc/example_markdown_files/md_ex1.md
markgdoc/example_markdown_files/md_ex2.md
markgdoc/example_markdown_files/md_ex3.md
markgdoc/example_markdown_files/md_ex4.md
markgdoc-1.1.1.dist-info/licenses/LICENSE
markgdoc-1.1.1.dist-info/METADATA
markgdoc-1.1.1.dist-info/WHEEL
markgdoc-1.1.1.dist-info/entry_points.txt
markgdoc-1.1.1.dist-info/top_level.txt
markgdoc-1.1.1.dist-info/RECORD
