Metadata-Version: 2.4
Name: markgdoc
Version: 1.1.1
Summary: A package where users can convert markdown syntax into their very own google docs file
Author-email: Aditya Pandhare <adityapandhare44@gmail.com>
License:                     GNU GENERAL PUBLIC LICENSE
Project-URL: Homepage, https://github.com/awesomeadi00/MarkGDoc
Project-URL: Repository, https://github.com/awesomeadi00/MarkGDoc.git
Project-URL: Bug Tracker, https://github.com/awesomeadi00/MarkGDoc/issues
Keywords: python,package,markdown,google-docs,requests
Classifier: Programming Language :: Python :: 3
Classifier: Intended Audience :: Education
Classifier: License :: OSI Approved :: GNU General Public License v3 (GPLv3)
Classifier: Operating System :: OS Independent
Requires-Python: >=3.7
License-File: LICENSE
Requires-Dist: google-auth
Requires-Dist: google-auth-oauthlib
Requires-Dist: google-auth-httplib2
Requires-Dist: google-api-python-client
Requires-Dist: tqdm
Requires-Dist: colorama
Provides-Extra: dev
Requires-Dist: pytest; extra == "dev"
Dynamic: license-file
